tests/__init__.py
tests/test_yafwi.py
yafwi/__init__.py
yafwi-1.0.1.dist-info/LICENSE
yafwi-1.0.1.dist-info/METADATA
yafwi-1.0.1.dist-info/WHEEL
yafwi-1.0.1.dist-info/top_level.txt
yafwi-1.0.1.dist-info/RECORD
