Metadata-Version: 2.1
Name: yafwi
Version: 1.0.1
Summary: Yet Another Fixed Width Integer (Library)
Home-page: https://github.com/buhanec/yafwi
Author: Alen Buhanec
Author-email: <alen.buhanec@gmail.com>
License: MIT
Platform: UNKNOWN
Classifier: Topic :: Software Development :: Libraries
Classifier: Development Status :: 4 - Beta
Classifier: Programming Language :: Python :: 3
Classifier: Programming Language :: Python :: 3.7
Classifier: Programming Language :: Python :: 3.8
Classifier: Programming Language :: Python :: 3.9
Classifier: License :: OSI Approved :: MIT License
Classifier: Operating System :: OS Independent
Classifier: Typing :: Typed
